bin/change_ip_utility.py
bin/ChangeIpUtility.exe
bin/device_info_utility.py
bin/DeviceInfoUtility.exe
bin/image_cal_utility.py
bin/ImageCalUtility.exe
bin/multi_channel_utility.py
bin/MultiChannelUtility.exe
bin/point_cloud_utility.py
bin/PointCloudUtility.exe
bin/rectified_focal_length_utility.py
bin/RectifiedFocalLengthUtility.exe
bin/save_image_utility.py
bin/SaveImageUtility.exe
bin/version_info_utility.py
bin/VersionInfoUtility.exe
include/MultiSense/MultiSenseChannel.hh
include/MultiSense/MultiSenseSerialization.hh
include/MultiSense/MultiSenseTypes.hh
include/MultiSense/MultiSenseUtilities.hh
include/MultiSense/utility/BufferStream.hh
include/MultiSense/utility/Exception.hh
include/MultiSense/utility/Portability.hh
include/MultiSense/utility/TimeStamp.hh
include/MultiSense/wire/AckMessage.hh
include/MultiSense/wire/ApriltagDetections.hh
include/MultiSense/wire/CamConfigMessage.hh
include/MultiSense/wire/CamControlMessage.hh
include/MultiSense/wire/CamGetConfigMessage.hh
include/MultiSense/wire/CamGetHistoryMessage.hh
include/MultiSense/wire/CamHistoryMessage.hh
include/MultiSense/wire/CamSetResolutionMessage.hh
include/MultiSense/wire/CamSetTriggerSourceMessage.hh
include/MultiSense/wire/DisparityMessage.hh
include/MultiSense/wire/ExposureConfigMessage.hh
include/MultiSense/wire/ImageMessage.hh
include/MultiSense/wire/ImageMetaMessage.hh
include/MultiSense/wire/ImuConfigMessage.hh
include/MultiSense/wire/ImuDataMessage.hh
include/MultiSense/wire/ImuGetConfigMessage.hh
include/MultiSense/wire/ImuGetInfoMessage.hh
include/MultiSense/wire/ImuInfoMessage.hh
include/MultiSense/wire/JpegMessage.hh
include/MultiSense/wire/LedGetSensorStatusMessage.hh
include/MultiSense/wire/LedGetStatusMessage.hh
include/MultiSense/wire/LedSensorStatusMessage.hh
include/MultiSense/wire/LedSetMessage.hh
include/MultiSense/wire/LedStatusMessage.hh
include/MultiSense/wire/LidarDataMessage.hh
include/MultiSense/wire/LidarPollMotorMessage.hh
libmultisense-7.4.0.dist-info/METADATA
libmultisense-7.4.0.dist-info/WHEEL
libmultisense-7.4.0.dist-info/licenses/LICENSE.TXT
libmultisense-7.4.0.dist-info/RECORD
