Metadata-Version: 2.2
Name: libmultisense
Version: 7.4.0
Summary: LibMultiSense python package wrapped using pybind11
Author-Email: Matt Alvarado <support@carnegierobotics.com>
Project-URL: Homepage, https://github.com/carnegierobotics/libmultisense
Project-URL: Issues, https://github.com/carnegierobotics/libmultisense/issues
Requires-Python: >=3.8
